Metadata-Version: 2.1
Name: MomwhyareyouhereTextAnalyzer
Version: 0.2.0
Summary: Text Analyzer
Author: Momwhyareyouhere
